preparse/__init__.py
preparse/_processing/__init__.py
preparse/_processing/deparsing.py
preparse/_processing/digesting.py
preparse/_processing/items.py
preparse/_processing/parsing.py
preparse/_processing/pulling.py
preparse/_utils/BaseData.py
preparse/_utils/__init__.py
preparse/_utils/dataprop.py
preparse/core/Click.py
preparse/core/Optdict.py
preparse/core/PreParser.py
preparse/core/__init__.py
preparse/core/enums.py
preparse/core/warnings.py
preparse/tests/__init__.py
preparse/tests/data.toml
preparse/tests/expit.toml
preparse/tests/test_data_toml.py
preparse/tests/test_expit_toml.py
preparse/tests/test_features.py
preparse-0.1.12.dist-info/licenses/LICENSE.txt
preparse-0.1.12.dist-info/METADATA
preparse-0.1.12.dist-info/WHEEL
preparse-0.1.12.dist-info/top_level.txt
preparse-0.1.12.dist-info/RECORD
