Metadata-Version: 2.4
Name: preparse
Version: 0.1.12
Summary: This project preparses args for further parsing later on.
Author-email: Johannes <johannes.programming@gmail.com>
License: The MIT License (MIT)
Project-URL: Download, https://pypi.org/project/preparse/#files
Project-URL: Index, https://pypi.org/project/preparse/
Project-URL: Source, https://github.com/johannes-programming/preparse/
Project-URL: Website, https://preparse.johannes-programming.online/
Classifier: Development Status :: 3 - Alpha
Classifier: License :: OSI Approved :: MIT License
Classifier: Natural Language :: English
Classifier: Operating System :: OS Independent
Classifier: Programming Language :: Python
Classifier: Programming Language :: Python :: 3
Classifier: Programming Language :: Python :: 3 :: Only
Classifier: Typing :: Typed
Requires-Python: >=3.11
License-File: LICENSE.txt
Requires-Dist: click<9,>=8.2
Requires-Dist: datahold<2,>=1.1.10
Requires-Dist: datarepr<2,>=1.0.2
Requires-Dist: overloadable<2,>=1.0.9
Requires-Dist: tofunc<2,>=1.0
Dynamic: license-file
